README.md
setup.py
histogram_plus/__init__.py
histogram_plus/bayesian_blocks_hep.py
histogram_plus/fill_between_steps.py
histogram_plus/hist_funcs.py
histogram_plus.egg-info/PKG-INFO
histogram_plus.egg-info/SOURCES.txt
histogram_plus.egg-info/dependency_links.txt
histogram_plus.egg-info/not-zip-safe
histogram_plus.egg-info/requires.txt
histogram_plus.egg-info/top_level.txt