Metadata-Version: 1.0
Name: histogram-plus
Version: 0.2.1
Summary: Overloaded histogram maker based on mpl
Home-page: http://github.com/brovercleveland/histogram_plus
Author: Brian Pollack
Author-email: brianleepollack@gmail.com
License: MIT
Keywords: histogram,physics,plotting
Platform: UNKNOWN
